eddyflux/__init__.py
eddyflux/meteo.py
eddyflux/base/__init__.py
eddyflux/base/correlate_delay.py
eddyflux/base/despike.py
eddyflux/base/raw.py
eddyflux/base/rotate_wind3D.py
eddyflux/base/rotate_wind3D_moving_platform.py
eddyflux/base/spectrum_analysis.py
eddyflux/base/eddyqc/CO2.py
eddyflux/base/eddyqc/Ts.py
eddyflux/base/eddyqc/__init__.py
eddyflux/base/eddyqc/mutual.py
eddyflux/base/eddyqc/qcutils.py
eddyflux/base/eddyspec/__init__.py
eddyflux/base/eddyspec/spectra_analysis.py
eddyflux/base/eddyspec/specutils.py
eddyflux/toolbox/__init__.py
eddyflux/toolbox/df2tob1.py
eddyflux/toolbox/edire.py
eddyflux/toolbox/utils.py
eddyflux-0.0.11.dist-info/METADATA
eddyflux-0.0.11.dist-info/WHEEL
eddyflux-0.0.11.dist-info/top_level.txt
eddyflux-0.0.11.dist-info/RECORD
