Metadata-Version: 2.1
Name: eddyflux
Version: 0.0.11
Summary: left blank
Home-page: UNKNOWN
Author: Songyan Zhu
Author-email: sz394@exeter.ac.uk
License: MIT Licence
Keywords: eddy covariance processing,flux
Platform: any
